appyx/__init__.py
appyx/layers/__init__.py
appyx/layers/application/__init__.py
appyx/layers/application/application.py
appyx/layers/application/environment.py
appyx/layers/application/exception_handler.py
appyx/layers/application/external_parameters.py
appyx/layers/application/test_application.py
appyx/layers/application/test_environment.py
appyx/layers/application/interactions/__init__.py
appyx/layers/application/interactions/app_interaction.py
appyx/layers/application/interactions/interaction.py
appyx/layers/application/interactions/proto_interaction.py
appyx/layers/application/interactions/proto_interaction_test.py
appyx/layers/application/interactions/simple_interaction.py
appyx/layers/application/interactions/test_app_interaction.py
appyx/layers/application/interactions/test_app_interaction_white_box.py
appyx/layers/application/interactions/test_simple_interaction.py
appyx/layers/application/interactions/parameters/__init__.py
appyx/layers/application/interactions/parameters/interaction_parameters.py
appyx/layers/application/interactions/parameters/parameter.py
appyx/layers/application/interactions/parameters/set_of_parameters.py
appyx/layers/application/interactions/parameters/test_command_parameters.py
appyx/layers/application/interactions/parameters/test_parameter.py
appyx/layers/application/interactions/validators/__init__.py
appyx/layers/application/interactions/validators/generic.py
appyx/layers/application/interactions/validators/parameters.py
appyx/layers/domain/__init__.py
appyx/layers/domain/business.py
appyx/layers/domain/errors.py
appyx/layers/domain/result.py
appyx/layers/domain/test_result.py
appyx/layers/domain/exceptions/__init__.py
appyx/layers/domain/exceptions/early_return.py
appyx/layers/domain/exceptions/message.py
appyx/layers/domain/messages/__init__.py
appyx/layers/domain/messages/error_messages.py
appyx/layers/domain/messages/exceptions.py
appyx/layers/domain/messages/message.py
appyx/layers/domain/messages/type_of_message.py
appyx-0.0.15.dist-info/LICENSE
appyx-0.0.15.dist-info/METADATA
appyx-0.0.15.dist-info/WHEEL
appyx-0.0.15.dist-info/top_level.txt
appyx-0.0.15.dist-info/RECORD
