Metadata-Version: 2.1
Name: appyx
Version: 0.0.15
Summary: Framework for building commercial applications
Home-page: https://gitlab.com/eryx/appyx
Author: Eryx Team
Author-email: info@eryx.co
License: MIT
Platform: UNKNOWN
Classifier: Development Status :: 3 - Alpha
Classifier: Intended Audience :: Developers
Classifier: Natural Language :: English
Classifier: Programming Language :: Python :: 3.7
Classifier: Topic :: Software Development
License-File: LICENSE
